README.rst
aiohttp_exc_handlers.py
setup.py
aiohttp_exc_handlers.egg-info/PKG-INFO
aiohttp_exc_handlers.egg-info/SOURCES.txt
aiohttp_exc_handlers.egg-info/dependency_links.txt
aiohttp_exc_handlers.egg-info/requires.txt
aiohttp_exc_handlers.egg-info/top_level.txt