Metadata-Version: 1.1
Name: aiohttp-exc-handlers
Version: 0.2
Summary: Bind views to exceptions for aiohttp
Home-page: https://github.com/zzzsochi/aiohttp_exc_handlers
Author: Alexander Zelenyak
Author-email: zzz.sochi@gmail.com
License: BSD
Keywords: asyncio,aiohttp
Platform: UNKNOWN
Classifier: License :: OSI Approved :: BSD License
Classifier: Operating System :: POSIX
Classifier: Programming Language :: Python :: 3.4
Classifier: Programming Language :: Python :: 3.5
Classifier: Topic :: Internet :: WWW/HTTP
